Metadata-Version: 2.1
Name: colorconverters
Version: 0.2.0
Summary: A useful package which handles the utilities of converting colors to different forms.
Home-page: https://github.com/ThatGenZGamer48/colorconverters
Author: GenZ Gamer
Author-email: thatgenzgamer@gmail.com
License: MIT
Project-URL: Documentation, https://github.com/ThatGenZGamer48/colorconverters/blob/main/README.rst
Project-URL: Issue tracker, https://github.com/ThatGenZGamer48/colorconverters/issues
Keywords: colors,converters,colorconverters
Platform: UNKNOWN
Classifier: Development Status :: 5 - Production/Stable
Classifier: Intended Audience :: Developers
Classifier: Operating System :: OS Independent
Classifier: License :: OSI Approved :: MIT License
Classifier: Programming Language :: Python :: 3
Classifier: Natural Language :: English
Classifier: Topic :: Internet
Classifier: Topic :: Software Development :: Libraries
Classifier: Topic :: Software Development :: Libraries :: Python Modules
Classifier: Topic :: Utilities
Classifier: Typing :: Typed
